sphero_sdk/__init__.py
sphero_sdk/__version__.py
sphero_sdk/asyncio/__init__.py
sphero_sdk/asyncio/client/__init__.py
sphero_sdk/asyncio/client/dal/__init__.py
sphero_sdk/asyncio/client/dal/restful_async_dal.py
sphero_sdk/asyncio/client/dal/serial_async_dal.py
sphero_sdk/asyncio/client/firmware/__init__.py
sphero_sdk/asyncio/client/firmware/rvr_fw_check_async.py
sphero_sdk/asyncio/client/toys/__init__.py
sphero_sdk/asyncio/client/toys/sphero_rvr_async.py
sphero_sdk/asyncio/config/__init__.py
sphero_sdk/asyncio/config/logging_config.py
sphero_sdk/asyncio/controls/__init__.py
sphero_sdk/asyncio/controls/drive_control_async.py
sphero_sdk/asyncio/controls/infrared_control_async.py
sphero_sdk/asyncio/controls/led_control_async.py
sphero_sdk/asyncio/controls/sensor_control_async.py
sphero_sdk/asyncio/server/__init__.py
sphero_sdk/asyncio/server/conftest.py
sphero_sdk/asyncio/server/handler/__init__.py
sphero_sdk/asyncio/server/handler/api_sphero_handler.py
sphero_sdk/asyncio/server/handler/sphero_handler_base.py
sphero_sdk/asyncio/server/parser/__init__.py
sphero_sdk/asyncio/server/parser/api_sphero_parser.py
sphero_sdk/asyncio/server/parser/sphero_parser_base.py
sphero_sdk/asyncio/server/port/__init__.py
sphero_sdk/asyncio/server/port/serial_sphero_port.py
sphero_sdk/asyncio/server/port/sphero_port_base.py
sphero_sdk/asyncio/server/service/__init__.py
sphero_sdk/asyncio/server/service/api_robo_service.py
sphero_sdk/asyncio/server/service/robo_service_base.py
sphero_sdk/asyncio/server/service/robo_service_channel.py
sphero_sdk/asyncio/server/service/sphero_robo_service.py
sphero_sdk/asyncio/server/toy/__init__.py
sphero_sdk/asyncio/server/toy/sphero_toy_base.py
sphero_sdk/common/__init__.py
sphero_sdk/common/devices.py
sphero_sdk/common/exceptions.py
sphero_sdk/common/helpers.py
sphero_sdk/common/log_level.py
sphero_sdk/common/parameter.py
sphero_sdk/common/rvr_streaming_services.py
sphero_sdk/common/sequence_number_generator.py
sphero_sdk/common/client/__init__.py
sphero_sdk-0.3.4.post2.dist-info/LICENSE.md
sphero_sdk-0.3.4.post2.dist-info/METADATA
sphero_sdk-0.3.4.post2.dist-info/WHEEL
sphero_sdk-0.3.4.post2.dist-info/top_level.txt
sphero_sdk-0.3.4.post2.dist-info/RECORD
